rab/__init__.py
rab/cli.py
rab/scripts/__init__.py
rab/server/__init__.py
rab/server/api.yaml
rab/server/handlers.py
rab/storage/__init__.py
rab/utils/__init__.py
rab/utils/annotations.py
rab/utils/cli_args.py
rab/utils/constants.py
rab/utils/discover.py
rab/utils/logging_utils.py
rab/utils/process.py
rab-0.2.0.dist-info/LICENSE
rab-0.2.0.dist-info/METADATA
rab-0.2.0.dist-info/WHEEL
rab-0.2.0.dist-info/entry_points.txt
rab-0.2.0.dist-info/top_level.txt
rab-0.2.0.dist-info/RECORD
