Metadata-Version: 2.1
Name: rab
Version: 0.2.0
Summary: REST API Base
Home-page: https://github.com/JHibbard/rest-api-base
Author: James Hibbard
License: MIT
Platform: UNKNOWN
Classifier: Programming Language :: Python :: 3.8
Classifier: License :: OSI Approved :: MIT License
Requires-Python: >=3.8
Requires-Dist: connexion[swagger-ui] (==2.7.0)
Requires-Dist: PyYAML (==5.3.1)
Requires-Dist: Flask (==1.1.2)
Requires-Dist: click (==7.1.2)
Requires-Dist: Flask-Cors (==3.0.9)
Requires-Dist: gunicorn (==20.0.4)
Provides-Extra: docs
Requires-Dist: Sphinx (==3.3.1) ; extra == 'docs'
Requires-Dist: sphinx-click (==2.5.0) ; extra == 'docs'
Provides-Extra: quality
Requires-Dist: black (==20.8b1) ; extra == 'quality'
Requires-Dist: pyflakes (==2.2.0) ; extra == 'quality'
Requires-Dist: radon (==4.3.2) ; extra == 'quality'
Provides-Extra: sqlalchemy
Requires-Dist: SQLAlchemy (==1.3.20) ; extra == 'sqlalchemy'
